{
  "signers": {
    "alfajores": {
      "key": "",
      "type": "hexKey"
    },
    "kovan": {
      "key": "",
      "type": "hexKey"
    }
  },
  "replicas": {
    "kovan": {
      "address": "0x47F55f3F0a82B73225E7e506f0feB6Ad53cd3B7e",
      "domain": "3000",
      "name": "kovan",
      "rpcStyle": "ethereum",
      "connection": {
        "type": "http",
        "url": "https://kovan.infura.io/v3/5c456d7844fa40a683e934df60534c60"
      }
    }
  },
  "home": {
    "address": "0x1CCB08D4d7212931e91efC8B89Ab7f52b7f29154",
    "domain": "1000",
    "name": "alfajores",
    "rpcStyle": "ethereum",
    "connection": {
      "type": "http",
      "url": "https://alfajores-forno.celo-testnet.org"
    }
  },
  "tracing": {
    "level": "debug",
    "style": "pretty"
  },
  "db": "db_path"
}